{
  "todo": [
    {
      "title": "nấu ăn ngon",
      "description": "Lorem Ipsum is simply dummy text of the printing and typesetting industry. Lorem Ipsum has been the industry's standard dummy",
      "id": "Ds5MsmKYP",
      "stt": 1
    },
    {
      "title": "One piece",
      "description": "Lorem Ipsum is simply dummy text of the printing and typesetting industry. Lorem Ipsum has been the industry's standard dummy",
      "id": "OXG6KXt8X",
      "stt": 2
    }
  ],
  "users": [
    {
      "name": "Nguyễn Xuân Quyết",
      "phone": "0357842534",
      "email": "quyetnxm04120@arena.edu.vn",
      "password": "123",
      "stt": 1,
      "id": "HNGVCS2Lj",
      "isAdmin": true
    },
    {
      "name": "Trongu",
      "phone": "0981618988",
      "email": "admin@gmail.com",
      "password": "123",
      "stt": 2,
      "id": "IBI5wCZa3",
      "isAdmin": false
    },
    {
      "name": "Tùng Dương",
      "phone": "0988888888",
      "email": "duong@gmail.com",
      "password": "123",
      "stt": 3,
      "id": "LjE5OYtX6",
      "isAdmin": false
    }
  ],
  "transection": [
    {
      "userId": "HNGVCS2Lj",
      "bookId": "Ds5MsmKYP",
      "id": "mcwNtSVeC",
      "stt": 1,
      "isComplete": false
    },
    {
      "userId": "IBI5wCZa3",
      "bookId": "Ds5MsmKYP",
      "id": "XVqrvTPfL",
      "stt": 2,
      "isComplete": true
    },
    {
      "userId": "LjE5OYtX6",
      "bookId": "Ds5MsmKYP",
      "id": "sjYor-O9J",
      "stt": 3,
      "isComplete": false
    },
    {
      "userId": "LjE5OYtX6",
      "bookId": "OXG6KXt8X",
      "id": "4U1gob2_x",
      "stt": 4,
      "isComplete": false
    },
    {
      "userId": "IBI5wCZa3",
      "bookId": "OXG6KXt8X",
      "id": "BFFd1gHkE",
      "stt": 5,
      "isComplete": false
    }
  ]
}